firewheel_repo_i2p/i2p_config_bandwidth/MANIFEST
firewheel_repo_i2p/i2p_config_bandwidth/README.md
firewheel_repo_i2p/i2p_config_bandwidth/advertised_bandwidth.py
firewheel_repo_i2p/i2p_config_bandwidth/vm_resources/random_failures.py
firewheel_repo_i2p/i2p_config_bandwidth/vm_resources/remove_old_maxmemory.sh
firewheel_repo_i2p/i2p_config_bandwidth/vm_resources/set_advertised_bandwidth.py
firewheel_repo_i2p/i2p_config_floodfills/MANIFEST
firewheel_repo_i2p/i2p_config_floodfills/README.md
firewheel_repo_i2p/i2p_config_floodfills/config_floodfills.py
firewheel_repo_i2p/i2p_config_floodfills/vm_resources/set_traffic_control.py
firewheel_repo_i2p/i2p_config_snark/MANIFEST
firewheel_repo_i2p/i2p_config_snark/README.md
firewheel_repo_i2p/i2p_config_snark/config_snark.py
firewheel_repo_i2p/i2p_config_snark/vm_resources/add_tracktor_address.py
firewheel_repo_i2p/i2p_config_snark/vm_resources/configure_i2psnark.py
firewheel_repo_i2p/i2p_config_snark/vm_resources/i2psnark_generate_torrent.py
firewheel_repo_i2p/i2p_config_snark/vm_resources/i2psnark_set_tracker.py
firewheel_repo_i2p/i2p_config_snark/vm_resources/i2psnark_subscribe_torrent.py
firewheel_repo_i2p/i2p_config_snark/vm_resources/reload_torrents.sh
firewheel_repo_i2p/i2p_config_victims/MANIFEST
firewheel_repo_i2p/i2p_config_victims/README.md
firewheel_repo_i2p/i2p_config_victims/config_victims.py
firewheel_repo_i2p/i2p_config_victims/victim_group_configs.json
firewheel_repo_i2p/i2p_config_victims/vg_configs/all_bw_victim_group_configs.json
firewheel_repo_i2p/i2p_config_victims/vg_configs/all_victim_group_configs.json
firewheel_repo_i2p/i2p_config_victims/vg_configs/dev_victim_group_configs.json
firewheel_repo_i2p/i2p_config_victims/vg_configs/mix2_victim_group_configs.json
firewheel_repo_i2p/i2p_config_victims/vg_configs/test_bw_victim_group_configs.json
firewheel_repo_i2p/i2p_config_victims/vg_configs/test_cores_victim_group_configs.json
firewheel_repo_i2p-2.7.0.dist-info/LICENSE
firewheel_repo_i2p-2.7.0.dist-info/METADATA
firewheel_repo_i2p-2.7.0.dist-info/WHEEL
firewheel_repo_i2p-2.7.0.dist-info/entry_points.txt
firewheel_repo_i2p-2.7.0.dist-info/top_level.txt
firewheel_repo_i2p-2.7.0.dist-info/RECORD
